[
    {
        "name": "Telegram",
        "color": "#0088cc",
        "icon": "telegram",
        "url": "https://t.me/AVEY_NATA"
	},
    {
        "name": "Instagram",
        "color": "#bc2a8d",
        "icon": "instagram",
        "url": "https://www.instagram.com/natanot"
	},
    {
        "name": "Github",
        "color": "black",
        "icon": "github-face",
        "url": "https://github.com/AVEYNT"
	},
    {
        "name": "Twitter",
        "color": "#00acee",
        "icon": "twitter",
        "url": "https://twitter.com/AVEYNT"
	},
    {
        "name": "Discord",
        "color": "#7289da",
        "icon": "discord",
        "url": "https://discord.gg/5dda5k5"
	}
]
